{"log_url": null, "num_elec": 10, "num_basis": 6, "correction": 0.0, "num_virtual": 1, "energy_total": -98.59495305578172, "num_occupied": 5, "mo_coefficients": {"key": "d68fa7bb2d25465bd2e4e44a64025f97f941a3bcc2eb3669d048658aa63316fa", "s3_url": "https://qemistmocoefficients.s3.us-west-2.amazonaws.com/d68fa7bb2d25465bd2e4e44a64025f97f941a3bcc2eb3669d048658aa63316fa", "s3_bucket_name": "qemistmocoefficients"}, "mp2_correlation": -0.01584310750078999, "mean_field_energy": -98.57075759161424, "energy_correlation": -0.024195464167462433, "virtual_orbital_space": [5], "complete_orbital_space": [0, 1, 2, 3, 4, 5], "occupied_orbital_space": [0, 1, 2, 3, 4], "frozen_orbitals_truncated": [0, 3, 4], "active_virtual_orbital_space": [5], "frozen_virtual_orbital_space": [], "mp2_active_space_correlation": -0.01584310750078999, "active_occupied_orbital_space": [1, 2], "frozen_occupied_orbital_space": [0, 3, 4], "active_virtual_orbital_space_truncated": [5], "frozen_virtual_orbital_space_truncated": [], "solve_time": 2, "sub_problems": []}